dcm_metrics/__init__.py
dcm_metrics/dcm_metrics.py
dcm_metrics-0.2.0.dist-info/WHEEL
dcm_metrics-0.2.0.dist-info/METADATA
dcm_metrics-0.2.0.dist-info/RECORD
