Metadata-Version: 2.1
Name: dcm-metrics
Version: 0.2.0
Summary: Package for sending metrics to Azure Application Insights
Author: Jan Lukány
Author-email: lukany.jan@gmail.com
Requires-Python: >=3.7.1,<4.0.0
Classifier: Programming Language :: Python :: 3
Classifier: Programming Language :: Python :: 3.8
Classifier: Programming Language :: Python :: 3.9
Requires-Dist: azure-identity (>=1.5.0,<2.0.0)
Requires-Dist: azure-keyvault (>=4.1.0,<5.0.0)
Requires-Dist: opencensus (>=0.7.12,<0.8.0)
Requires-Dist: opencensus-ext-azure (>=1.0.7,<2.0.0)
